LICENSE
README.md
setup.py
mcpi_listener/__init__.py
mcpi_listener/mcpi_listener.py
mcpi_listener.egg-info/PKG-INFO
mcpi_listener.egg-info/SOURCES.txt
mcpi_listener.egg-info/dependency_links.txt
mcpi_listener.egg-info/not-zip-safe
mcpi_listener.egg-info/requires.txt
mcpi_listener.egg-info/top_level.txt